dotini/__init__.py
dotini-0.0.1.dist-info/LICENSE.txt
dotini-0.0.1.dist-info/METADATA
dotini-0.0.1.dist-info/WHEEL
dotini-0.0.1.dist-info/top_level.txt
dotini-0.0.1.dist-info/RECORD
