Metadata-Version: 2.1
Name: dotini
Version: 0.0.1
Summary: Dot notation for configuration files.
Home-page: https://github.com/cloudsickle/dotini
Author: James Thomas Kirkpatrick IV
License: MIT
Keywords: configuration settings ini cfg config
Platform: UNKNOWN
